{"title":"Topic 001 Question 022","body":["You have a Fabric capacity that contains a workspace named Workspace1. Workspace1 contains a lakehouse named Lakehouse1, a data pipeline, a notebook, and several Microsoft Power BI reports.","A user named User1 wants to use SQL to analyze the data in Lakehouse1.","You need to configure access for User1. The solution must meet the following requirements:","Provide User1 with read access to the table data in Lakehouse1.","Prevent User1 from using Apache Spark to query the underlying files in Lakehouse1.","Prevent User1 from accessing other items in Workspace1.","What should you do?\r"],"options":["Share Lakehouse1 with User1 directly and select Read all SQL endpoint data.\r","Assign User1 the Viewer role for Workspace1. Share Lakehouse1 with User1 and select Read all SQL endpoint data.\r","Share Lakehouse1 with User1 directly and select Build reports on the default semantic model.\r","Assign User1 the Member role for Workspace1. Share Lakehouse1 with User1 and select Read all SQL endpoint data.\r"],"answer":"A","et_answer":"A"}