{"title":"Topic 001 Question 033","body":["A customer wants to move their sensitive workloads to a Compute Engine-based cluster using Managed Instance Groups (MIGs). The jobs are bursty and must be completed quickly. They have a requirement to be able to control the key lifecycle.","Which boot disk encryption solution should you use on the cluster to meet this customer's requirements?",""],"options":["Customer-supplied encryption keys (CSEK)","Customer-managed encryption keys (CMEK) using Cloud Key Management Service (KMS)","Encryption by default","Pre-encrypting files before transferring to Google Cloud Platform (GCP) for analysis"],"answer":"B","et_answer":"x"}
