{"title":"Topic 002 Question 015","body":["You need to be alerted when users share sensitive documents from Microsoft OneDrive to any users outside your company.","What should you do?","\r"],"options":["From the Microsoft 365 compliance center, create a data loss prevention (DLP) policy.\r","From the Microsoft 365 compliance center, start a data investigation.\r","From the Microsoft 365 compliance center, create an insider risk policy.\r","From the Cloud App Security portal, create an activity policy.\r"],"answer":"A","et_answer":"A"}