{"title":"Topic 004 Question 074","body":["You have an Azure subscription, a Google Cloud Platform (GCP) account, and an Amazon Web Services (AWS) account.","","You need to recommend a solution to assess the risks associated with privilege assignments across all the platforms. The solution must minimize administrative effort.","","What should you include in the recommendation?\r"],"options":["Microsoft Sentinel\r","Microsoft Entra ID Protection\r","Microsoft Defender for Cloud Apps\r","Microsoft Entra Permissions Management\r"],"answer":"D","et_answer":"D"}