{"title":"Topic 002 Question 020","body":["You need to build a solution that will use optical character recognition (OCR) to scan sensitive documents by using the Computer Vision API. The solution must","NOT be deployed to the public cloud.","What should you do?","\r"],"options":["Build an on-premises web app to query the Computer Vision endpoint.\r","Host the Computer Vision endpoint in a container on an on-premises server.\r","Host an exported Open Neural Network Exchange (ONNX) model on an on-premises server.\r","Build an Azure web app to query the Computer Vision endpoint.\r"],"answer":"B","et_answer":"B"}