{"title":"Topic 005 Question 018","body":["SIMULATION -","You need to create and publish a bot that will use Language Understanding and QnA Maker. The bot must be named bot12345678. You must publish the bot by using the User1-12345678@abc.com account.","NOTE: Complete this task first. It may take several minutes to complete the required deployment steps. While this is taking place, you can complete tasks 2-6 in this lab during the deployment.","To complete this task, use the Microsoft Bot Framework Composer.",""],"options":[],"answer":"","et_answer":"x"}
