{"title":"Topic 004 Question 013","body":["HOTSPOT"," -","","You create a knowledge store for Azure Cognitive Search by using the following JSON.","","<img>/Microsoft AI-102/img/image16.png<img>","","Use the drop-down menus to select the answer choice that completes each statement based on the information presented in the graphic.","","NOTE: Each correct selection is worth one point.","","<img>/Microsoft AI-102/img/image17.png<img>"],"options":["<img>/Microsoft AI-102/img/image18.png<img>"],"answer":"","et_answer":""}
