{"title":"Topic 008 Question 002","body":["You have an Azure subscription that contains an Azure AI Content Safety resource named CS1.","","You create a test image that contains a circle.","","You submit the test image to CS1 by using the curl command and the following command-line parameters.","","\u003cimg\u003e/\u003ca href=\"/exams/microsoft\" style=\"color:black;\"\u003eMicrosoft\u003c/a\u003e AI-102/img/image192.png\u003cimg\u003e","","What should you expect as the output?\r"],"options":["0\r","0.0\r","7\r","100\r"],"answer":"A","et_answer":"A"}