{"title":"Topic 001 Question 312","body":["A company that operates in the AWS Cloud wants to test workloads and team responses to simulated events. The company will conduct an exercise to identify potential issues that need to be addressed.","","Which design principle of the AWS Well-Architected Framework does this exercise represent?"],"options":["Anticipate failure.","Automatically recover from failure.","Measure overall cost efficiency.","Implement loosely coupled dependencies."],"answer":"A","et_answer":"x"}
