{"title":"Topic 006 Question 026","body":["HOTSPOT"," -","","You have a Microsoft Sentinel workspace.","","You need to configure the Fusion analytics rule to temporarily suppress incidents generated by a Microsoft Defender connector. The solution must meet the following requirements:","","•\tMinimize impact on the ability to detect multistage attacks.","•\tMinimize administrative effort.","","How should you configure the rule? To answer, select the appropriate options in the answer area.","","NOTE: Each correct selection is worth one point.","","\u003cimg\u003e/\u003ca href=\"/exams/microsoft\" style=\"color:black;\"\u003eMicrosoft\u003c/a\u003e SC-200/img/image326.png\u003cimg\u003e"],"options":["\u003cimg\u003e/\u003ca href=\"/exams/microsoft\" style=\"color:black;\"\u003eMicrosoft\u003c/a\u003e SC-200/img/image327.png\u003cimg\u003e"],"answer":"","et_answer":""}