{"title":"Topic 004 Question 015","body":["You have a SQL pool in Azure Synapse.","A user reports that queries against the pool take longer than expected to complete. You determine that the issue relates to queried columnstore segments.","You need to add monitoring to the underlying storage to help diagnose the issue.","Which two metrics should you monitor? Each correct answer presents part of the solution.","NOTE: Each correct selection is worth one point.",""],"options":["Snapshot Storage Size","Cache used percentage","DWU Limit","Cache hit percentage"],"answer":"BD","et_answer":"x"}
