{"title":"Topic 001 Question 155","body":["A company has an initiative to reduce costs associated with Amazon EC2 and AWS Lambda.","","Which action should a SysOps administrator take to meet these requirements?"],"options":["Analyze the AWS Cost and Usage Report by using Amazon Athena to identify cost savings.","Create an AWS Budgets alert to alarm when account spend reaches 80% of the budget.","Purchase Reserved Instances through the Amazon EC2 console.","Use AWS Compute Optimizer and take action on the provided recommendations."],"answer":"D","et_answer":"x"}
