{"title":"Topic 003 Question 020","body":["In Power BI Desktop, you have a dataset that contains a table.","You create a table visual on a Power BI report page as shown in the following exhibit.","<img>/Microsoft PL-300/img/0021600001.jpg<img>","You need to configure the visual to display the referenced image instead of the URL in the Plant Image column.","What should you do?",""],"options":["From the Formatting tab, select Values, and then set URL icons to On for the table.","Set the Data category of the Plant Image field to Web URL.","Set the Data type of the Plant Image field to Binary.","Set the Data category of the Plant Image field to Image URL."],"answer":"D","et_answer":"x"}
