{"title":"Topic 001 Question 176","body":["Two Amazon EC2 instances in different subnets should be able to connect to each other but cannot. It has been confirmed that other hosts in the same subnets are able to communicate successfully, and that security groups have valid ALLOW rules in place to permit this traffic.","Which of the following troubleshooting steps should be performed?",""],"options":["Check inbound and outbound security groups, looking for DENY rules","Check inbound and outbound Network ACL rules, looking for DENY rules","Review the rejected packet reason codes in the VPC Flow Logs","Use AWS X-Ray to trace the end-to-end application flow"],"answer":"B","et_answer":"x"}
