{"title":"Topic 002 Question 001","body":["HOTSPOT -","You plan to deploy two Azure Stack Hub integrated systems named AZStack1 and AZStack2.","AZStack1 must meet the following requirements:","✑ Connect to the Internet.","✑ Have minimal capital expenditures.","✑ Use the minimum number of on-premises servers for identity.","✑ Have no existing licenses for Windows virtual machines deployed.","AZStack2 must meet the following requirements:","✑ Be disconnected from the Internet.","✑ Use the minimum number of on-premises servers for identity.","✑ Support the syndication of Azure Stack Hub Marketplace items.","Which identity provider and licensing model should you use for each integrated system? To answer, select the appropriate options in the answer area.","NOTE: Each correct selection is worth one point.","Hot Area:","\u003cimg\u003e/Microsoft AZ-600/img/0003300001.jpg\u003cimg\u003e","\r"],"options":["\u003cimg\u003e/Microsoft AZ-600/img/0003300002.jpg\u003cimg\u003e"],"answer":"","et_answer":""}