{"title":"Topic 005 Question 006","body":["You have 1,000 devices that connect to an Azure IoT hub.","You are performing a scheduled check of deployed IoT devices.","You plan to run the following command from the Azure CLI prompt. az iot hub query --hub-name hub1 --query-command \"SELECT * FROM devices WHERE connectionState = 'Disconnected'\"","What does the command return?","\r"],"options":["the Device Disconnected events\r","the device twins\r","the Connections logs\r","the device credentials\r"],"answer":"","et_answer":"B"}