{"title":"Topic 001 Question 004","body":["HOTSPOT -","A company uses Azure Backup Agent to back up specific files and folders from an on-premises virtual machine (VM).","An administrator reports that the backup job is transferring files slowly. You determine that the backup job is verifying changes in directories by scanning the entire volume.","You need to determine the state of the backup job.","In which state will the backups occur? To answer, select the appropriate options in the answer area.","NOTE: Each correct selection is worth one point.","<img>/Microsoft AZ-720/img/image3.png<img>"],"options":["<img>/Microsoft AZ-720/img/image4.png<img>"],"answer":"","et_answer":""}
