{"title":"Topic 001 Question 088","body":["You have new security and governance protocols for Power BI reports and datasets. The new protocols must meet the following requirements:","New reports can be embedded only in locations that require authentication.","Live connections are permitted only for workspaces that use Premium capacity datasets.","Which three actions should you recommend performing in the Power BI Admin portal? Each correct answer presents part of the solution.","NOTE: Each correct selection is worth one point.\r"],"options":["From Embed Codes, delete all the codes.\r","From Tenant settings, disable Allow XMLA endpoints and Analyze in Excel with on-premises datasets.\r","From Capacity settings, set XMLA Endpoint to Read Write.\r","From the Premium per user settings, set XMLA Endpoint to Off.\r","From Tenant settings, set Publish to web to Disable.\r"],"answer":"ADE","et_answer":"BCE"}