{"title":"Topic 001 Question 037","body":["You open a Power BI Desktop report that contains an imported data model and a single report page.","You open Performance analyzer, start recording, and refresh the visuals on the page. The recording produces the results shown in the following exhibit.","\u003cimg\u003e/Microsoft DP-500/img/image39.png\u003cimg\u003e","What can you identify from the results?\r"],"options":["When all the visuals refresh simultaneously, the visuals spend most of the time waiting on other processes to finish.\r","The Actual/Forecast Billable Hrs YTD visual displays the most data.\r","Unoptimized DAX queries cause the page to load slowly.\r","The Actual/Forecast Hours by Type visual takes a long time to render on the report page when the data is cross-filtered.\r"],"answer":"A","et_answer":"A"}