{"title":"Topic 003 Question 030","body":["HOTSPOT -","You are developing a web application by using the Azure SDK. The web application accesses data in a zone-redundant BlockBlobStorage storage account.","The application must determine whether the data has changed since the application last read the data. Update operations must use the latest data changes when writing data to the storage account.","You need to implement the update operations.","Which values should you use? To answer, select the appropriate option in the answer area.","NOTE: Each correct selection is worth one point.","Hot Area:","\u003cimg\u003e/Microsoft AZ-204/img/0026600001.png\u003cimg\u003e","\r"],"options":["\u003cimg\u003e/Microsoft AZ-204/img/0026700001.png\u003cimg\u003e"],"answer":"","et_answer":""}