{"title":"Topic 002 Question 012","body":["DRAG DROP -","You are developing a serverless Java application on Azure. You create a new Azure Key Vault to work with secrets from a new Azure Functions application.","The application must meet the following requirements:","✑ Reference the Azure Key Vault without requiring any changes to the Java code.","✑ Dynamically add and remove instances of the Azure Functions host based on the number of incoming application events.","✑ Ensure that instances are perpetually warm to avoid any cold starts.","✑ Connect to a VNet.","✑ Authentication to the Azure Key Vault instance must be removed if the Azure Function application is deleted.","You need to grant the Azure Functions application access to the Azure Key Vault.","Which three actions should you perform in sequence? To answer, move the appropriate actions from the list of actions to the answer area and arrange them in the correct order.","Select and Place:","<img>/Microsoft AZ-204/img/0010800001.png<img>",""],"options":["<img>/Microsoft AZ-204/img/0010900001.png<img>"],"answer":"","et_answer":""}
