{"title":"Topic 004 Question 053","body":["You purchase an Azure subscription. You plan to deploy resources shown in the following table to the subscription.","","\u003cimg\u003e/\u003ca href=\"/exams/microsoft\" style=\"color:black;\"\u003eMicrosoft\u003c/a\u003e AZ-700/img/image448.png\u003cimg\u003e","","You need to create a NSG1 rule named Rule1 to meet the following requirements:","","•\tEnable the search servers of App1 to establish outbound HTTP connections to internet services.","•\tMinimize administrative effort when new search servers are deployed.","•\tUse the principle of least privilege.","","What should you select as the source for Rule1?\r"],"options":["Application security group\r","IP Addresses\r","Any\r","VirtualNetwork\r"],"answer":"A","et_answer":"B"}