{
    "title": "Topic 001 Question 051",
    "body": [
        "You have an on-premises datacenter named Site1 that contains a firewall named FW1. FW1 connects to the internet.",
        "",
        "You have an Azure subscription that contains the resources shown in the following table.",
        "",
        "<img>/Microsoft AZ-700/img/image479.png<img>",
        "",
        "You plan to connect Site1 to Hub1 by using a site-to-site connection.",
        "",
        "You need to configure the site-to-site connection to FW1.",
        "",
        "What should you create in VWAN1?\r"
    ],
    "options": [
        "a VPN site\r",
        "a virtual network connection\r",
        "a network virtual appliance (NVA)\r",
        "a User VPN configuration\r"
    ],
    "answer": "A",
    "et_answer": "A"
}