{"title":"Topic 003 Question 070","body":["HOTSPOT"," -","","You have an Azure subscription.","","You plan to deploy the virtual machines shown in the following table.","","\u003cimg\u003e/\u003ca href=\"https://www.examtopics.com/exams/microsoft\" style=\"color:black;\"\u003eMicrosoft\u003c/a\u003e AZ-500/img/image802.png\u003cimg\u003e","","You need to identify the virtual machines and operating systems that can be deployed as confidential virtual machines?","","Which Windows virtual machines and which Linux virtual machines should you identify?","","\u003cimg\u003e/\u003ca href=\"https://www.examtopics.com/exams/microsoft\" style=\"color:black;\"\u003eMicrosoft\u003c/a\u003e AZ-500/img/image803.png\u003cimg\u003e"],"options":["\u003cimg\u003e/\u003ca href=\"https://www.examtopics.com/exams/microsoft\" style=\"color:black;\"\u003eMicrosoft\u003c/a\u003e AZ-500/img/image804.png\u003cimg\u003e"],"answer":"","et_answer":""}