{"title":"Topic 003 Question 043","body":["You have an Azure subscription that contains an Azure Container Registry named Registry1. Microsoft Defender for Cloud is enabled in the subscription.","You upload several container images to Registry1.","You discover that vulnerability security scans were not performed.","You need to ensure that the container images are scanned for vulnerabilities when they are uploaded to Registry1.","What should you do?","\r"],"options":["From the Azure portal, modify the Pricing tier settings.\r","From Azure CLI, lock the container images.\r","Upload the container images by using AzCopy.\r","Push the container images to Registry1 by using Docker.\r"],"answer":"A","et_answer":"A"}