{"title":"Topic 003 Question 038","body":["You have the Azure virtual machines shown in the following table.","\u003cimg\u003e/\u003ca href=\"https://www.examtopics.com/exams/microsoft\" style=\"color:black;\"\u003eMicrosoft\u003c/a\u003e AZ-500/img/0027900001.png\u003cimg\u003e","You create an Azure Log Analytics workspace named Analytics1 in RG1 in the East US region.","Which virtual machines can be enrolled in Analytics1?","\r"],"options":["VM1 only\r","VM1, VM2, and VM3 only\r","VM1, VM2, VM3, and VM4\r","VM1 and VM4 only\r"],"answer":"C","et_answer":"C"}